Workbook

Sheet README
A1: Shopee & Monee unit economics, Q1 2019 - Q2 2026
A2: Source: Sea Limited (NYSE: SE) quarterly earnings releases (Form 6-K, exhibit 99.1) on SEC EDGAR. Each Data row links to its filing.
A3: Question: is Shopee's growth becoming more profitable, is Monee's fast loan growth staying healthy, and, before H2 is reported, how likely is the 'US$1 billion Shopee adjusted EBITDA in FY2026' expectation (nowcast as of 15 Oct 2026)?
A5: How to read this file
A6: - Yellow cells on Target_2026 are assumptions you can change. Everything else is a formula or a reported number.
A7: - Money in US$ millions unless the column says bn. Take rates and margins are % of GMV unless stated otherwise.
A9: Definitions
A10: - GMV: value of goods sold on Shopee. Gross orders: number of orders. Average order value (AOV) = GMV / gross orders.
A11: - Marketplace revenue = core marketplace revenue (transaction fees + advertising) + value-added services (mainly logistics). Shopee's own product sales are excluded.
A12: - Take rate = revenue / GMV. Core take rate uses core marketplace revenue only (reported since Q3 2022).
A13: - Adjusted EBITDA (Sea's segment measure) = operating income + depreciation & amortization. Share-based compensation is unallocated, not in Shopee's figure.
A15: Data notes and limits
... A23: - No country split: Sea does not report Shopee Indonesia separately.

Sheet Data
A1: Period | B1: Release date | C1: GMV (US$ bn) | D1: GMV source | E1: Gross orders (bn) | F1: Orders source | G1: GMV YoY reported % | H1: Orders YoY reported % | I1: Shopee revenue (US$ m) | J1: Marketplace revenue (US$ m) | K1: Core marketplace revenue (US$ m) | L1: Value-added services revenue (US$ m) | M1: Shopee adj. EBITDA (US$ m) | N1: Monee revenue (US$ m) | O1: Monee adj. EBITDA (US$ m) | P1: Monee loans (US$ bn) | Q1: Loan basis | R1: NPL 90+ days % | S1: NPL as reported (bounds) | T1: Source filing
A2: 2019Q1 | B2: 2019-05-22 | C2: 3.5 | D2: reported | E2: 0.2035 | F2: reported | G2: 81.8 | H2: 82.7 | I2: 149.2 | J2: 102 | M2: -235.253 | O2: -11.912 | T2: 6-K ex.99.1
A3: 2019Q2 | B3: 2019-08-20 | C3: 3.8 | D3: reported | E3: 0.2463 | F3: reported | G3: 72.3 | H3: 92.7 | I3: 177.4 | J3: 137.8 | M3: -248.251 | O3: -18.144 | T3: 6-K ex.99.1
A4: 2019Q3 | B4: 2019-11-12 | C4: 4.6 | D4: reported | E4: 0.3214 | F4: reported | G4: 69.9 | H4: 102.8 | I4: 257.2 | J4: 208.1 | M4: -253.712 | O4: -33.628 | T4: 6-K ex.99.1
A5: 2019Q4 | B5: 2020-03-03 | C5: 5.6 | D5: reported | E5: 0.4405 | F5: reported | G5: 64.8 | H5: 112.9 | I5: 358.3 | J5: 283.5 | M5: -306.15 | O5: -49.761 | T5: 6-K ex.99.1
A6: 2020Q1 | B6: 2020-05-18 | C6: 6.2 | D6: reported | E6: 0.4298 | F6: reported | G6: 74.3 | H6: 111.2 | I6: 314 | J6: 236.7 | M6: -260.019 | O6: -101.583 | T6: 6-K ex.99.1
A7: 2020Q2 | B7: 2020-08-18 | C7: 8 | D7: reported | E7: 0.6159 | F7: reported | G7: 109.9 | H7: 150.1 | I7: 510.6 | J7: 378.7 | M7: -305.477 | O7: -110.105 | T7: 6-K ex.99.1
A8: 2020Q3 | B8: 2020-11-17 | C8: 9.3 | D8: reported | E8: 0.7416 | F8: reported | G8: 102.7 | H8: 130.7 | I8: 618.7 | J8: 467.1 | M8: -301.59 | O8: -149.263 | T8: 6-K ex.99.1
A9: 2020Q4 | B9: 2021-03-02 | C9: 11.9 | D9: reported | E9: 1 | F9: reported | G9: 112.5 | H9: 134.6 | I9: 842.2 | J9: 627.6 | M9: -427.474 | O9: -171.263 | T9: 6-K ex.99.1
A10: 2021Q1 | B10: 2021-05-18 | C10: 12.6 | D10: reported | E10: 1.1 | F10: reported | G10: 103.2 | H10: 153 | I10: 922.3 | J10: 715.9 | M10: -412.897 | O10: -153.088 | T10: 6-K ex.99.1
A11: 2021Q2 | B11: 2021-08-17 | C11: 15 | D11: reported | E11: 1.4 | F11: reported | G11: 87.5 | H11: 127.4 | I11: 1200 | J11: 904.6 | M11: -579.774 | O11: -154.986 | T11: 6-K ex.99.1
A12: 2021Q3 | B12: 2021-11-16 | C12: 16.8 | D12: reported | E12: 1.7 | F12: reported | G12: 80.6 | H12: 123.2 | I12: 1500 | J12: 1200 | M12: -683.813 | O12: -159.037 | T12: 6-K ex.99.1
A13: 2021Q4 | B13: 2022-03-01 | C13: 18.2 | D13: reported | E13: 2 | F13: reported | G13: 52.7 | H13: 90.1 | I13: 1600 | J13: 1300 | M13: -877.737 | N13: 197.5 | O13: -149.813 | T13: 6-K ex.99.1
A14: 2022Q1 | B14: 2022-05-17 | C14: 17.4 | D14: reported | E14: 1.9 | F14: reported | G14: 38.7 | H14: 71.3 | I14: 1500 | J14: 1300 | M14: -742.82 | N14: 236 | O14: -124.898 | T14: 6-K ex.99.1
A15: 2022Q2 | B15: 2022-08-16 | C15: 19 | D15: reported | E15: 2 | F15: reported | G15: 27.2 | H15: 41.6 | I15: 1700 | J15: 1500 | M15: -648.145 | N15: 279 | O15: -111.517 | T15: 6-K ex.99.1
A16: 2022Q3 | B16: 2022-11-15 | C16: 19.1 | D16: reported | E16: 2 | F16: reported | G16: 13.5 | H16: 19.2 | I16: 1900 | J16: 1600 | K16: 1000 | L16: 600 | M16: -495.735 | N16: 326.9 | O16: -67.746 | P16: 2.2 | Q16: net loans receivable, on-book | S16: <4% | T16: 6-K ex.99.1
A17: 2022Q4 | B17: 2023-03-07 | C17: 18 | D17: reported | E17: 1.7 | F17: reported | I17: 2100 | J17: 1800 | K17: 1100 | L17: 700 | M17: 196.146 | N17: 380.2 | O17: 75.601 | P17: 2.1 | Q17: net loans receivable, on-book | S17: <2% | T17: 6-K ex.99.1
A18: 2023Q1 | B18: 2023-05-16 | C18: 17.315 | D18: derived from 2024Q1 YoY | E18: 1.658 | F18: derived from 2024Q1 YoY | I18: 2100 | J18: 1800 | K18: 1200 | L18: 700 | M18: 207.714 | N18: 412.8 | O18: 98.938 | P18: 2 | Q18: net loans receivable, on-book | S18: ~2% | T18: 6-K ex.99.1
A19: 2023Q2 | B19: 2023-08-15 | C19: 18.048 | D19: derived from 2024Q2 YoY | E19: 1.782 | F19: derived from 2024Q2 YoY | I19: 2100 | J19: 1900 | K19: 1200 | L19: 625.2 | M19: 150.339 | N19: 427.9 | O19: 136.961 | P19: 2 | Q19: net loans receivable, on-book | S19: ~2% | T19: 6-K ex.99.1
A20: 2023Q3 | B20: 2023-11-14 | C20: 20.1 | D20: reported | E20: 2.2 | F20: reported | G20: 5.1 | H20: 13.2 | I20: 2200 | J20: 1900 | K20: 1300 | L20: 592.8 | M20: -346.495 | N20: 446.2 | O20: 165.731 | P20: 2.4 | Q20: gross loans receivable, on-book | R20: 1.6 | T20: 6-K ex.99.1
A21: 2023Q4 | B21: 2024-03-04 | C21: 23.1 | D21: reported | E21: 2.5 | F21: reported | G21: 28.6 | H21: 46 | I21: 2600 | J21: 2300 | K21: 1600 | L21: 657.9 | M21: -225.332 | N21: 472.4 | O21: 148.482 | P21: 3.1 | Q21: principal outstanding, on- and off-book | R21: 1.6 | T21: 6-K ex.99.1
A22: 2024Q1 | B22: 2024-05-14 | C22: 23.6 | D22: reported | E22: 2.6 | F22: reported | G22: 36.3 | H22: 56.8 | I22: 2700 | J22: 2422.74 | K22: 1700.24 | L22: 722.5 | M22: -21.7 | N22: 499.364 | O22: 148.658 | P22: 3.3 | Q22: principal outstanding, on- and off-book | R22: 1.4 | T22: 6-K ex.99.1
A23: 2024Q2 | B23: 2024-08-13 | C23: 23.3 | D23: reported | E23: 2.5 | F23: reported | G23: 29.1 | H23: 40.3 | I23: 2800 | J23: 2479.83 | K23: 1757.53 | L23: 722.3 | M23: -9.18 | N23: 519.338 | O23: 164.678 | P23: 3.5 | Q23: principal outstanding, on- and off-book | R23: 1.3 | T23: 6-K ex.99.1
A24: 2024Q3 | B24: 2024-11-12 | C24: 25.1 | D24: reported | E24: 2.8 | F24: reported | G24: 25.2 | H24: 24.2 | I24: 3200 | J24: 2767.163 | K24: 1999.963 | L24: 767.2 | M24: 34.446 | N24: 615.711 | O24: 187.927 | P24: 4.6 | Q24: principal outstanding, on- and off-book | R24: 1.2 | T24: 6-K ex.99.1
A25: 2024Q4 | B25: 2025-03-04 | C25: 28.6 | D25: reported | E25: 3 | F25: reported | G25: 23.5 | H25: 20.1 | I25: 3700 | J25: 3192.53 | K25: 2397.73 | L25: 794.8 | M25: 152.209 | N25: 733.326 | O25: 210.979 | P25: 5.1 | Q25: principal outstanding, on- and off-book | R25: 1.2 | T25: 6-K ex.99.1
A26: 2025Q1 | B26: 2025-05-13 | C26: 28.6 | D26: reported | E26: 3.1 | F26: reported | G26: 21.5 | H26: 20.5 | I26: 3500 | J26: 3118.931 | K26: 2366.731 | L26: 752.2 | M26: 264.417 | N26: 787.117 | O26: 241.439 | P26: 5.8 | Q26: principal outstanding, on- and off-book | R26: 1.1 | T26: 6-K ex.99.1
A27: 2025Q2 | B27: 2025-08-12 | C27: 29.8 | D27: reported | E27: 3.3 | F27: reported | G27: 28.2 | H27: 28.6 | I27: 3800 | J27: 3312.155 | K27: 2569.155 | L27: 743 | M27: 227.694 | N27: 882.808 | O27: 255.263 | P27: 6.9 | Q27: principal outstanding, on- and off-book | R27: 1 | T27: 6-K ex.99.1
A28: 2025Q3 | B28: 2025-11-12 | C28: 32.2 | D28: reported | E28: 3.6 | F28: reported | G28: 28.4 | H28: 28.4 | I28: 4300 | J28: 3778.68 | K28: 3055.08 | L28: 723.6 | M28: 186.055 | N28: 989.861 | O28: 258.312 | P28: 7.9 | Q28: principal outstanding, on- and off-book | R28: 1.1 | T28: 6-K ex.99.1
A29: 2025Q4 | B29: 2026-03-03 | C29: 36.7 | D29: reported | E29: 4 | F29: reported | G29: 28.6 | H29: 30.5 | I29: 5000 | J29: 4336.128 | K29: 3601.128 | L29: 735 | M29: 202.457 | N29: 1131.855 | O29: 263.07 | P29: 9.2 | Q29: principal outstanding, on- and off-book | R29: 1.1 | T29: 6-K ex.99.1
A30: 2026Q1 | B30: 2026-05-12 | C30: 37.3 | D30: reported | E30: 4 | F30: reported | G30: 30.2 | H30: 29.3 | I30: 5100 | J30: 4503.11 | K30: 3811.51 | L30: 691.6 | M30: 223.174 | N30: 1241.782 | O30: 275.243 | P30: 9.9 | Q30: principal outstanding, on- and off-book | R30: 1.1 | T30: 6-K ex.99.1
A31: 2026Q2 | B31: 2026-08-11 | C31: 38.3 | D31: reported | E31: 4.2 | F31: reported | G31: 28.4 | H31: 27.5 | I31: 5600 | J31: 4931.861 | K31: 4255.461 | L31: 676.4 | M31: 255.419 | N31: 1402.83 | O31: 287.985 | P31: 11.1 | Q31: principal outstanding, on- and off-book | R31: 1 | T31: 6-K ex.99.1

Sheet Shopee_Metrics
A1: Period | B1: AOV (US$ per order) | C1: Marketplace take rate | D1: Core take rate (fees + ads) | E1: VAS (logistics) % GMV | F1: Adj. EBITDA per order (US$) | G1: Adj. EBITDA % GMV | H1: Adj. EBITDA % marketplace revenue | I1: GMV YoY | J1: Orders YoY | K1: Marketplace revenue YoY | L1: Trailing 4Q GMV (US$ bn) | M1: Trailing 4Q adj. EBITDA (US$ m)
A2: =Data!A2 -> 2019Q1 | B2: =IF(OR(Data!C2="",Data!E2=""),"",Data!C2/Data!E2) -> 17.199017 | C2: =IF(OR(Data!J2="",Data!C2=""),"",Data!J2/(Data!C2*1000)) -> 0.029142857 | D2: =IF(OR(Data!K2=""),"",Data!K2/(Data!C2*1000)) | E2: =IF(OR(Data!L2=""),"",Data!L2/(Data!C2*1000)) | F2: =IF(OR(Data!E2=""),"",Data!M2/(Data!E2*1000)) -> -1.1560344 | G2: =IF(OR(Data!C2=""),"",Data!M2/(Data!C2*1000)) -> -0.067215143 | H2: =IF(OR(Data!J2=""),"",Data!M2/Data!J2) -> -2.306402
A3: =Data!A3 -> 2019Q2 | B3: =IF(OR(Data!C3="",Data!E3=""),"",Data!C3/Data!E3) -> 15.428339 | C3: =IF(OR(Data!J3="",Data!C3=""),"",Data!J3/(Data!C3*1000)) -> 0.036263158 | D3: =IF(OR(Data!K3=""),"",Data!K3/(Data!C3*1000)) | E3: =IF(OR(Data!L3=""),"",Data!L3/(Data!C3*1000)) | F3: =IF(OR(Data!E3=""),"",Data!M3/(Data!E3*1000)) -> -1.0079212 | G3: =IF(OR(Data!C3=""),"",Data!M3/(Data!C3*1000)) -> -0.065329211 | H3: =IF(OR(Data!J3=""),"",Data!M3/Data!J3) -> -1.8015312
A4: =Data!A4 -> 2019Q3 | B4: =IF(OR(Data!C4="",Data!E4=""),"",Data!C4/Data!E4) -> 14.312383 | C4: =IF(OR(Data!J4="",Data!C4=""),"",Data!J4/(Data!C4*1000)) -> 0.04523913 | D4: =IF(OR(Data!K4=""),"",Data!K4/(Data!C4*1000)) | E4: =IF(OR(Data!L4=""),"",Data!L4/(Data!C4*1000)) | F4: =IF(OR(Data!E4=""),"",Data!M4/(Data!E4*1000)) -> -0.78939639 | G4: =IF(OR(Data!C4=""),"",Data!M4/(Data!C4*1000)) -> -0.055154783 | H4: =IF(OR(Data!J4=""),"",Data!M4/Data!J4) -> -1.2191831
A5: =Data!A5 -> 2019Q4 | B5: =IF(OR(Data!C5="",Data!E5=""),"",Data!C5/Data!E5) -> 12.712826 | C5: =IF(OR(Data!J5="",Data!C5=""),"",Data!J5/(Data!C5*1000)) -> 0.050625 | D5: =IF(OR(Data!K5=""),"",Data!K5/(Data!C5*1000)) | E5: =IF(OR(Data!L5=""),"",Data!L5/(Data!C5*1000)) | F5: =IF(OR(Data!E5=""),"",Data!M5/(Data!E5*1000)) -> -0.69500568 | G5: =IF(OR(Data!C5=""),"",Data!M5/(Data!C5*1000)) -> -0.054669643 | H5: =IF(OR(Data!J5=""),"",Data!M5/Data!J5) -> -1.0798942 | L5: =SUM(Data!C2:C5) -> 17.5 | M5: =SUM(Data!M2:M5) -> -1043.366
A6: =Data!A6 -> 2020Q1 | B6: =IF(OR(Data!C6="",Data!E6=""),"",Data!C6/Data!E6) -> 14.425314 | C6: =IF(OR(Data!J6="",Data!C6=""),"",Data!J6/(Data!C6*1000)) -> 0.038177419 | D6: =IF(OR(Data!K6=""),"",Data!K6/(Data!C6*1000)) | E6: =IF(OR(Data!L6=""),"",Data!L6/(Data!C6*1000)) | F6: =IF(OR(Data!E6=""),"",Data!M6/(Data!E6*1000)) -> -0.60497673 | G6: =IF(OR(Data!C6=""),"",Data!M6/(Data!C6*1000)) -> -0.041938548 | H6: =IF(OR(Data!J6=""),"",Data!M6/Data!J6) -> -1.0985171 | I6: =IF(OR(Data!C6="",Data!C2=""),"",Data!C6/Data!C2-1) -> 0.77142857 | J6: =IF(OR(Data!E6="",Data!E2=""),"",Data!E6/Data!E2-1) -> 1.1120393 | K6: =IF(OR(Data!J6="",Data!J2=""),"",Data!J6/Data!J2-1) -> 1.3205882 | L6: =SUM(Data!C3:C6) -> 20.2 | M6: =SUM(Data!M3:M6) -> -1068.132
A7: =Data!A7 -> 2020Q2 | B7: =IF(OR(Data!C7="",Data!E7=""),"",Data!C7/Data!E7) -> 12.989122 | C7: =IF(OR(Data!J7="",Data!C7=""),"",Data!J7/(Data!C7*1000)) -> 0.0473375 | D7: =IF(OR(Data!K7=""),"",Data!K7/(Data!C7*1000)) | E7: =IF(OR(Data!L7=""),"",Data!L7/(Data!C7*1000)) | F7: =IF(OR(Data!E7=""),"",Data!M7/(Data!E7*1000)) -> -0.49598474 | G7: =IF(OR(Data!C7=""),"",Data!M7/(Data!C7*1000)) -> -0.038184625 | H7: =IF(OR(Data!J7=""),"",Data!M7/Data!J7) -> -0.80664642 | I7: =IF(OR(Data!C7="",Data!C3=""),"",Data!C7/Data!C3-1) -> 1.1052632 | J7: =IF(OR(Data!E7="",Data!E3=""),"",Data!E7/Data!E3-1) -> 1.500609 | K7: =IF(OR(Data!J7="",Data!J3=""),"",Data!J7/Data!J3-1) -> 1.7481858 | L7: =SUM(Data!C4:C7) -> 24.4 | M7: =SUM(Data!M4:M7) -> -1125.358
A8: =Data!A8 -> 2020Q3 | B8: =IF(OR(Data!C8="",Data!E8=""),"",Data!C8/Data!E8) -> 12.540453 | C8: =IF(OR(Data!J8="",Data!C8=""),"",Data!J8/(Data!C8*1000)) -> 0.050225806 | D8: =IF(OR(Data!K8=""),"",Data!K8/(Data!C8*1000)) | E8: =IF(OR(Data!L8=""),"",Data!L8/(Data!C8*1000)) | F8: =IF(OR(Data!E8=""),"",Data!M8/(Data!E8*1000)) -> -0.40667476 | G8: =IF(OR(Data!C8=""),"",Data!M8/(Data!C8*1000)) -> -0.032429032 | H8: =IF(OR(Data!J8=""),"",Data!M8/Data!J8) -> -0.64566474 | I8: =IF(OR(Data!C8="",Data!C4=""),"",Data!C8/Data!C4-1) -> 1.0217391 | J8: =IF(OR(Data!E8="",Data!E4=""),"",Data!E8/Data!E4-1) -> 1.3074051 | K8: =IF(OR(Data!J8="",Data!J4=""),"",Data!J8/Data!J4-1) -> 1.2445939 | L8: =SUM(Data!C5:C8) -> 29.1 | M8: =SUM(Data!M5:M8) -> -1173.236
A9: =Data!A9 -> 2020Q4 | B9: =IF(OR(Data!C9="",Data!E9=""),"",Data!C9/Data!E9) -> 11.9 | C9: =IF(OR(Data!J9="",Data!C9=""),"",Data!J9/(Data!C9*1000)) -> 0.052739496 | D9: =IF(OR(Data!K9=""),"",Data!K9/(Data!C9*1000)) | E9: =IF(OR(Data!L9=""),"",Data!L9/(Data!C9*1000)) | F9: =IF(OR(Data!E9=""),"",Data!M9/(Data!E9*1000)) -> -0.427474 | G9: =IF(OR(Data!C9=""),"",Data!M9/(Data!C9*1000)) -> -0.035922185 | H9: =IF(OR(Data!J9=""),"",Data!M9/Data!J9) -> -0.68112492 | I9: =IF(OR(Data!C9="",Data!C5=""),"",Data!C9/Data!C5-1) -> 1.125 | J9: =IF(OR(Data!E9="",Data!E5=""),"",Data!E9/Data!E5-1) -> 1.2701476 | K9: =IF(OR(Data!J9="",Data!J5=""),"",Data!J9/Data!J5-1) -> 1.2137566 | L9: =SUM(Data!C6:C9) -> 35.4 | M9: =SUM(Data!M6:M9) -> -1294.56
A10: =Data!A10 -> 2021Q1 | B10: =IF(OR(Data!C10="",Data!E10=""),"",Data!C10/Data!E10) -> 11.454545 | C10: =IF(OR(Data!J10="",Data!C10=""),"",Data!J10/(Data!C10*1000)) -> 0.05681746 | D10: =IF(OR(Data!K10=""),"",Data!K10/(Data!C10*1000)) | E10: =IF(OR(Data!L10=""),"",Data!L10/(Data!C10*1000)) | F10: =IF(OR(Data!E10=""),"",Data!M10/(Data!E10*1000)) -> -0.37536091 | G10: =IF(OR(Data!C10=""),"",Data!M10/(Data!C10*1000)) -> -0.032769603 | H10: =IF(OR(Data!J10=""),"",Data!M10/Data!J10) -> -0.57675234 | I10: =IF(OR(Data!C10="",Data!C6=""),"",Data!C10/Data!C6-1) -> 1.0322581 | J10: =IF(OR(Data!E10="",Data!E6=""),"",Data!E10/Data!E6-1) -> 1.5593299 | K10: =IF(OR(Data!J10="",Data!J6=""),"",Data!J10/Data!J6-1) -> 2.0245036 | L10: =SUM(Data!C7:C10) -> 41.8 | M10: =SUM(Data!M7:M10) -> -1447.438
A11: =Data!A11 -> 2021Q2 | B11: =IF(OR(Data!C11="",Data!E11=""),"",Data!C11/Data!E11) -> 10.714286 | C11: =IF(OR(Data!J11="",Data!C11=""),"",Data!J11/(Data!C11*1000)) -> 0.060306667 | D11: =IF(OR(Data!K11=""),"",Data!K11/(Data!C11*1000)) | E11: =IF(OR(Data!L11=""),"",Data!L11/(Data!C11*1000)) | F11: =IF(OR(Data!E11=""),"",Data!M11/(Data!E11*1000)) -> -0.41412429 | G11: =IF(OR(Data!C11=""),"",Data!M11/(Data!C11*1000)) -> -0.0386516 | H11: =IF(OR(Data!J11=""),"",Data!M11/Data!J11) -> -0.64091753 | I11: =IF(OR(Data!C11="",Data!C7=""),"",Data!C11/Data!C7-1) -> 0.875 | J11: =IF(OR(Data!E11="",Data!E7=""),"",Data!E11/Data!E7-1) -> 1.2730963 | K11: =IF(OR(Data!J11="",Data!J7=""),"",Data!J11/Data!J7-1) -> 1.3886982 | L11: =SUM(Data!C8:C11) -> 48.8 | M11: =SUM(Data!M8:M11) -> -1721.735
A12: =Data!A12 -> 2021Q3 | B12: =IF(OR(Data!C12="",Data!E12=""),"",Data!C12/Data!E12) -> 9.8823529 | C12: =IF(OR(Data!J12="",Data!C12=""),"",Data!J12/(Data!C12*1000)) -> 0.071428571 | D12: =IF(OR(Data!K12=""),"",Data!K12/(Data!C12*1000)) | E12: =IF(OR(Data!L12=""),"",Data!L12/(Data!C12*1000)) | F12: =IF(OR(Data!E12=""),"",Data!M12/(Data!E12*1000)) -> -0.40224294 | G12: =IF(OR(Data!C12=""),"",Data!M12/(Data!C12*1000)) -> -0.040703155 | H12: =IF(OR(Data!J12=""),"",Data!M12/Data!J12) -> -0.56984417 | I12: =IF(OR(Data!C12="",Data!C8=""),"",Data!C12/Data!C8-1) -> 0.80645161 | J12: =IF(OR(Data!E12="",Data!E8=""),"",Data!E12/Data!E8-1) -> 1.2923409 | K12: =IF(OR(Data!J12="",Data!J8=""),"",Data!J12/Data!J8-1) -> 1.569043 | L12: =SUM(Data!C9:C12) -> 56.3 | M12: =SUM(Data!M9:M12) -> -2103.958
A13: =Data!A13 -> 2021Q4 | B13: =IF(OR(Data!C13="",Data!E13=""),"",Data!C13/Data!E13) -> 9.1 | C13: =IF(OR(Data!J13="",Data!C13=""),"",Data!J13/(Data!C13*1000)) -> 0.071428571 | D13: =IF(OR(Data!K13=""),"",Data!K13/(Data!C13*1000)) | E13: =IF(OR(Data!L13=""),"",Data!L13/(Data!C13*1000)) | F13: =IF(OR(Data!E13=""),"",Data!M13/(Data!E13*1000)) -> -0.4388685 | G13: =IF(OR(Data!C13=""),"",Data!M13/(Data!C13*1000)) -> -0.048227308 | H13: =IF(OR(Data!J13=""),"",Data!M13/Data!J13) -> -0.67518231 | I13: =IF(OR(Data!C13="",Data!C9=""),"",Data!C13/Data!C9-1) -> 0.52941176 | J13: =IF(OR(Data!E13="",Data!E9=""),"",Data!E13/Data!E9-1) -> 1 | K13: =IF(OR(Data!J13="",Data!J9=""),"",Data!J13/Data!J9-1) -> 1.071383 | L13: =SUM(Data!C10:C13) -> 62.6 | M13: =SUM(Data!M10:M13) -> -2554.221
A14: =Data!A14 -> 2022Q1 | B14: =IF(OR(Data!C14="",Data!E14=""),"",Data!C14/Data!E14) -> 9.1578947 | C14: =IF(OR(Data!J14="",Data!C14=""),"",Data!J14/(Data!C14*1000)) -> 0.074712644 | D14: =IF(OR(Data!K14=""),"",Data!K14/(Data!C14*1000)) | E14: =IF(OR(Data!L14=""),"",Data!L14/(Data!C14*1000)) | F14: =IF(OR(Data!E14=""),"",Data!M14/(Data!E14*1000)) -> -0.39095789 | G14: =IF(OR(Data!C14=""),"",Data!M14/(Data!C14*1000)) -> -0.042690805 | H14: =IF(OR(Data!J14=""),"",Data!M14/Data!J14) -> -0.5714 | I14: =IF(OR(Data!C14="",Data!C10=""),"",Data!C14/Data!C10-1) -> 0.38095238 | J14: =IF(OR(Data!E14="",Data!E10=""),"",Data!E14/Data!E10-1) -> 0.72727273 | K14: =IF(OR(Data!J14="",Data!J10=""),"",Data!J14/Data!J10-1) -> 0.81589607 | L14: =SUM(Data!C11:C14) -> 67.4 | M14: =SUM(Data!M11:M14) -> -2884.144
A15: =Data!A15 -> 2022Q2 | B15: =IF(OR(Data!C15="",Data!E15=""),"",Data!C15/Data!E15) -> 9.5 | C15: =IF(OR(Data!J15="",Data!C15=""),"",Data!J15/(Data!C15*1000)) -> 0.078947368 | D15: =IF(OR(Data!K15=""),"",Data!K15/(Data!C15*1000)) | E15: =IF(OR(Data!L15=""),"",Data!L15/(Data!C15*1000)) | F15: =IF(OR(Data!E15=""),"",Data!M15/(Data!E15*1000)) -> -0.3240725 | G15: =IF(OR(Data!C15=""),"",Data!M15/(Data!C15*1000)) -> -0.034112895 | H15: =IF(OR(Data!J15=""),"",Data!M15/Data!J15) -> -0.43209667 | I15: =IF(OR(Data!C15="",Data!C11=""),"",Data!C15/Data!C11-1) -> 0.26666667 | J15: =IF(OR(Data!E15="",Data!E11=""),"",Data!E15/Data!E11-1) -> 0.42857143 | K15: =IF(OR(Data!J15="",Data!J11=""),"",Data!J15/Data!J11-1) -> 0.65819147 | L15: =SUM(Data!C12:C15) -> 71.4 | M15: =SUM(Data!M12:M15) -> -2952.515
A16: =Data!A16 -> 2022Q3 | B16: =IF(OR(Data!C16="",Data!E16=""),"",Data!C16/Data!E16) -> 9.55 | C16: =IF(OR(Data!J16="",Data!C16=""),"",Data!J16/(Data!C16*1000)) -> 0.083769634 | D16: =IF(OR(Data!K16=""),"",Data!K16/(Data!C16*1000)) -> 0.052356021 | E16: =IF(OR(Data!L16=""),"",Data!L16/(Data!C16*1000)) -> 0.031413613 | F16: =IF(OR(Data!E16=""),"",Data!M16/(Data!E16*1000)) -> -0.2478675 | G16: =IF(OR(Data!C16=""),"",Data!M16/(Data!C16*1000)) -> -0.025954712 | H16: =IF(OR(Data!J16=""),"",Data!M16/Data!J16) -> -0.30983437 | I16: =IF(OR(Data!C16="",Data!C12=""),"",Data!C16/Data!C12-1) -> 0.13690476 | J16: =IF(OR(Data!E16="",Data!E12=""),"",Data!E16/Data!E12-1) -> 0.17647059 | K16: =IF(OR(Data!J16="",Data!J12=""),"",Data!J16/Data!J12-1) -> 0.33333333 | L16: =SUM(Data!C13:C16) -> 73.7 | M16: =SUM(Data!M13:M16) -> -2764.437
A17: =Data!A17 -> 2022Q4 | B17: =IF(OR(Data!C17="",Data!E17=""),"",Data!C17/Data!E17) -> 10.588235 | C17: =IF(OR(Data!J17="",Data!C17=""),"",Data!J17/(Data!C17*1000)) -> 0.1 | D17: =IF(OR(Data!K17=""),"",Data!K17/(Data!C17*1000)) -> 0.061111111 | E17: =IF(OR(Data!L17=""),"",Data!L17/(Data!C17*1000)) -> 0.038888889 | F17: =IF(OR(Data!E17=""),"",Data!M17/(Data!E17*1000)) -> 0.11538 | G17: =IF(OR(Data!C17=""),"",Data!M17/(Data!C17*1000)) -> 0.010897 | H17: =IF(OR(Data!J17=""),"",Data!M17/Data!J17) -> 0.10897 | I17: =IF(OR(Data!C17="",Data!C13=""),"",Data!C17/Data!C13-1) -> -0.010989011 | J17: =IF(OR(Data!E17="",Data!E13=""),"",Data!E17/Data!E13-1) -> -0.15 | K17: =IF(OR(Data!J17="",Data!J13=""),"",Data!J17/Data!J13-1) -> 0.38461538 | L17: =SUM(Data!C14:C17) -> 73.5 | M17: =SUM(Data!M14:M17) -> -1690.554
... A31: =Data!A31 -> 2026Q2 | B31: =IF(OR(Data!C31="",Data!E31=""),"",Data!C31/Data!E31) -> 9.1190476 | C31: =IF(OR(Data!J31="",Data!C31=""),"",Data!J31/(Data!C31*1000)) -> 0.12876922 | D31: =IF(OR(Data!K31=""),"",Data!K31/(Data!C31*1000)) -> 0.11110864 | E31: =IF(OR(Data!L31=""),"",Data!L31/(Data!C31*1000)) -> 0.017660574 | F31: =IF(OR(Data!E31=""),"",Data!M31/(Data!E31*1000)) -> 0.060814048 | G31: =IF(OR(Data!C31=""),"",Data!M31/(Data!C31*1000)) -> 0.0066689034 | H31: =IF(OR(Data!J31=""),"",Data!M31/Data!J31) -> 0.051789578 | I31: =IF(OR(Data!C31="",Data!C27=""),"",Data!C31/Data!C27-1) -> 0.2852349 | J31: =IF(OR(Data!E31="",Data!E27=""),"",Data!E31/Data!E27-1) -> 0.27272727 | K31: =IF(OR(Data!J31="",Data!J27=""),"",Data!J31/Data!J27-1) -> 0.48901878 | L31: =SUM(Data!C28:C31) -> 144.5 | M31: =SUM(Data!M28:M31) -> 867.105

Sheet Growth_Drivers
A1: Period | B1: Marketplace revenue YoY (= orders x AOV x take rate) | C1: Share from more orders | D1: Share from AOV | E1: Share from higher take rate
A2: =Data!A2 -> 2019Q1
A3: =Data!A3 -> 2019Q2
A4: =Data!A4 -> 2019Q3
A5: =Data!A5 -> 2019Q4
A6: =Data!A6 -> 2020Q1 | B6: =IFERROR(EXP(LN(Data!E6/Data!E2)+LN(Shopee_Metrics!B6/Shopee_Metrics!B2)+LN(Shopee_Metrics!C6/Shopee_Metrics!C2))-1,"") -> 1.3205882 | C6: =IFERROR(LN(Data!E6/Data!E2)/(LN(Data!E6/Data!E2)+LN(Shopee_Metrics!B6/Shopee_Metrics!B2)+LN(Shopee_Metrics!C6/Shopee_Metrics!C2)),"") -> 0.88813922 | D6: =IFERROR(LN(Shopee_Metrics!B6/Shopee_Metrics!B2)/(LN(Data!E6/Data!E2)+LN(Shopee_Metrics!B6/Shopee_Metrics!B2)+LN(Shopee_Metrics!C6/Shopee_Metrics!C2)),"") -> -0.20891344 | E6: =IFERROR(LN(Shopee_Metrics!C6/Shopee_Metrics!C2)/(LN(Data!E6/Data!E2)+LN(Shopee_Metrics!B6/Shopee_Metrics!B2)+LN(Shopee_Metrics!C6/Shopee_Metrics!C2)),"") -> 0.32077422
A7: =Data!A7 -> 2020Q2 | B7: =IFERROR(EXP(LN(Data!E7/Data!E3)+LN(Shopee_Metrics!B7/Shopee_Metrics!B3)+LN(Shopee_Metrics!C7/Shopee_Metrics!C3))-1,"") -> 1.7481858 | C7: =IFERROR(LN(Data!E7/Data!E3)/(LN(Data!E7/Data!E3)+LN(Shopee_Metrics!B7/Shopee_Metrics!B3)+LN(Shopee_Metrics!C7/Shopee_Metrics!C3)),"") -> 0.90661505 | D7: =IFERROR(LN(Shopee_Metrics!B7/Shopee_Metrics!B3)/(LN(Data!E7/Data!E3)+LN(Shopee_Metrics!B7/Shopee_Metrics!B3)+LN(Shopee_Metrics!C7/Shopee_Metrics!C3)),"") -> -0.17023134 | E7: =IFERROR(LN(Shopee_Metrics!C7/Shopee_Metrics!C3)/(LN(Data!E7/Data!E3)+LN(Shopee_Metrics!B7/Shopee_Metrics!B3)+LN(Shopee_Metrics!C7/Shopee_Metrics!C3)),"") -> 0.26361628
A8: =Data!A8 -> 2020Q3 | B8: =IFERROR(EXP(LN(Data!E8/Data!E4)+LN(Shopee_Metrics!B8/Shopee_Metrics!B4)+LN(Shopee_Metrics!C8/Shopee_Metrics!C4))-1,"") -> 1.2445939 | C8: =IFERROR(LN(Data!E8/Data!E4)/(LN(Data!E8/Data!E4)+LN(Shopee_Metrics!B8/Shopee_Metrics!B4)+LN(Shopee_Metrics!C8/Shopee_Metrics!C4)),"") -> 1.0341349 | D8: =IFERROR(LN(Shopee_Metrics!B8/Shopee_Metrics!B4)/(LN(Data!E8/Data!E4)+LN(Shopee_Metrics!B8/Shopee_Metrics!B4)+LN(Shopee_Metrics!C8/Shopee_Metrics!C4)),"") -> -0.16346498 | E8: =IFERROR(LN(Shopee_Metrics!C8/Shopee_Metrics!C4)/(LN(Data!E8/Data!E4)+LN(Shopee_Metrics!B8/Shopee_Metrics!B4)+LN(Shopee_Metrics!C8/Shopee_Metrics!C4)),"") -> 0.12933006
A9: =Data!A9 -> 2020Q4 | B9: =IFERROR(EXP(LN(Data!E9/Data!E5)+LN(Shopee_Metrics!B9/Shopee_Metrics!B5)+LN(Shopee_Metrics!C9/Shopee_Metrics!C5))-1,"") -> 1.2137566 | C9: =IFERROR(LN(Data!E9/Data!E5)/(LN(Data!E9/Data!E5)+LN(Shopee_Metrics!B9/Shopee_Metrics!B5)+LN(Shopee_Metrics!C9/Shopee_Metrics!C5)),"") -> 1.0316525 | D9: =IFERROR(LN(Shopee_Metrics!B9/Shopee_Metrics!B5)/(LN(Data!E9/Data!E5)+LN(Shopee_Metrics!B9/Shopee_Metrics!B5)+LN(Shopee_Metrics!C9/Shopee_Metrics!C5)),"") -> -0.083143058 | E9: =IFERROR(LN(Shopee_Metrics!C9/Shopee_Metrics!C5)/(LN(Data!E9/Data!E5)+LN(Shopee_Metrics!B9/Shopee_Metrics!B5)+LN(Shopee_Metrics!C9/Shopee_Metrics!C5)),"") -> 0.05149058
A10: =Data!A10 -> 2021Q1 | B10: =IFERROR(EXP(LN(Data!E10/Data!E6)+LN(Shopee_Metrics!B10/Shopee_Metrics!B6)+LN(Shopee_Metrics!C10/Shopee_Metrics!C6))-1,"") -> 2.0245036 | C10: =IFERROR(LN(Data!E10/Data!E6)/(LN(Data!E10/Data!E6)+LN(Shopee_Metrics!B10/Shopee_Metrics!B6)+LN(Shopee_Metrics!C10/Shopee_Metrics!C6)),"") -> 0.84910598 | D10: =IFERROR(LN(Shopee_Metrics!B10/Shopee_Metrics!B6)/(LN(Data!E10/Data!E6)+LN(Shopee_Metrics!B10/Shopee_Metrics!B6)+LN(Shopee_Metrics!C10/Shopee_Metrics!C6)),"") -> -0.20835652 | E10: =IFERROR(LN(Shopee_Metrics!C10/Shopee_Metrics!C6)/(LN(Data!E10/Data!E6)+LN(Shopee_Metrics!B10/Shopee_Metrics!B6)+LN(Shopee_Metrics!C10/Shopee_Metrics!C6)),"") -> 0.35925054
A11: =Data!A11 -> 2021Q2 | B11: =IFERROR(EXP(LN(Data!E11/Data!E7)+LN(Shopee_Metrics!B11/Shopee_Metrics!B7)+LN(Shopee_Metrics!C11/Shopee_Metrics!C7))-1,"") -> 1.3886982 | C11: =IFERROR(LN(Data!E11/Data!E7)/(LN(Data!E11/Data!E7)+LN(Shopee_Metrics!B11/Shopee_Metrics!B7)+LN(Shopee_Metrics!C11/Shopee_Metrics!C7)),"") -> 0.94303106 | D11: =IFERROR(LN(Shopee_Metrics!B11/Shopee_Metrics!B7)/(LN(Data!E11/Data!E7)+LN(Shopee_Metrics!B11/Shopee_Metrics!B7)+LN(Shopee_Metrics!C11/Shopee_Metrics!C7)),"") -> -0.22111349 | E11: =IFERROR(LN(Shopee_Metrics!C11/Shopee_Metrics!C7)/(LN(Data!E11/Data!E7)+LN(Shopee_Metrics!B11/Shopee_Metrics!B7)+LN(Shopee_Metrics!C11/Shopee_Metrics!C7)),"") -> 0.27808243
A12: =Data!A12 -> 2021Q3 | B12: =IFERROR(EXP(LN(Data!E12/Data!E8)+LN(Shopee_Metrics!B12/Shopee_Metrics!B8)+LN(Shopee_Metrics!C12/Shopee_Metrics!C8))-1,"") -> 1.569043 | C12: =IFERROR(LN(Data!E12/Data!E8)/(LN(Data!E12/Data!E8)+LN(Shopee_Metrics!B12/Shopee_Metrics!B8)+LN(Shopee_Metrics!C12/Shopee_Metrics!C8)),"") -> 0.87922002 | D12: =IFERROR(LN(Shopee_Metrics!B12/Shopee_Metrics!B8)/(LN(Data!E12/Data!E8)+LN(Shopee_Metrics!B12/Shopee_Metrics!B8)+LN(Shopee_Metrics!C12/Shopee_Metrics!C8)),"") -> -0.25246484 | E12: =IFERROR(LN(Shopee_Metrics!C12/Shopee_Metrics!C8)/(LN(Data!E12/Data!E8)+LN(Shopee_Metrics!B12/Shopee_Metrics!B8)+LN(Shopee_Metrics!C12/Shopee_Metrics!C8)),"") -> 0.37324482
A13: =Data!A13 -> 2021Q4 | B13: =IFERROR(EXP(LN(Data!E13/Data!E9)+LN(Shopee_Metrics!B13/Shopee_Metrics!B9)+LN(Shopee_Metrics!C13/Shopee_Metrics!C9))-1,"") -> 1.071383 | C13: =IFERROR(LN(Data!E13/Data!E9)/(LN(Data!E13/Data!E9)+LN(Shopee_Metrics!B13/Shopee_Metrics!B9)+LN(Shopee_Metrics!C13/Shopee_Metrics!C9)),"") -> 0.95184215 | D13: =IFERROR(LN(Shopee_Metrics!B13/Shopee_Metrics!B9)/(LN(Data!E13/Data!E9)+LN(Shopee_Metrics!B13/Shopee_Metrics!B9)+LN(Shopee_Metrics!C13/Shopee_Metrics!C9)),"") -> -0.36838492 | E13: =IFERROR(LN(Shopee_Metrics!C13/Shopee_Metrics!C9)/(LN(Data!E13/Data!E9)+LN(Shopee_Metrics!B13/Shopee_Metrics!B9)+LN(Shopee_Metrics!C13/Shopee_Metrics!C9)),"") -> 0.41654277
A14: =Data!A14 -> 2022Q1 | B14: =IFERROR(EXP(LN(Data!E14/Data!E10)+LN(Shopee_Metrics!B14/Shopee_Metrics!B10)+LN(Shopee_Metrics!C14/Shopee_Metrics!C10))-1,"") -> 0.81589607 | C14: =IFERROR(LN(Data!E14/Data!E10)/(LN(Data!E14/Data!E10)+LN(Shopee_Metrics!B14/Shopee_Metrics!B10)+LN(Shopee_Metrics!C14/Shopee_Metrics!C10)),"") -> 0.91612956 | D14: =IFERROR(LN(Shopee_Metrics!B14/Shopee_Metrics!B10)/(LN(Data!E14/Data!E10)+LN(Shopee_Metrics!B14/Shopee_Metrics!B10)+LN(Shopee_Metrics!C14/Shopee_Metrics!C10)),"") -> -0.37508912 | E14: =IFERROR(LN(Shopee_Metrics!C14/Shopee_Metrics!C10)/(LN(Data!E14/Data!E10)+LN(Shopee_Metrics!B14/Shopee_Metrics!B10)+LN(Shopee_Metrics!C14/Shopee_Metrics!C10)),"") -> 0.45895956
A15: =Data!A15 -> 2022Q2 | B15: =IFERROR(EXP(LN(Data!E15/Data!E11)+LN(Shopee_Metrics!B15/Shopee_Metrics!B11)+LN(Shopee_Metrics!C15/Shopee_Metrics!C11))-1,"") -> 0.65819147 | C15: =IFERROR(LN(Data!E15/Data!E11)/(LN(Data!E15/Data!E11)+LN(Shopee_Metrics!B15/Shopee_Metrics!B11)+LN(Shopee_Metrics!C15/Shopee_Metrics!C11)),"") -> 0.70527097 | D15: =IFERROR(LN(Shopee_Metrics!B15/Shopee_Metrics!B11)/(LN(Data!E15/Data!E11)+LN(Shopee_Metrics!B15/Shopee_Metrics!B11)+LN(Shopee_Metrics!C15/Shopee_Metrics!C11)),"") -> -0.23784777 | E15: =IFERROR(LN(Shopee_Metrics!C15/Shopee_Metrics!C11)/(LN(Data!E15/Data!E11)+LN(Shopee_Metrics!B15/Shopee_Metrics!B11)+LN(Shopee_Metrics!C15/Shopee_Metrics!C11)),"") -> 0.5325768
A16: =Data!A16 -> 2022Q3 | B16: =IFERROR(EXP(LN(Data!E16/Data!E12)+LN(Shopee_Metrics!B16/Shopee_Metrics!B12)+LN(Shopee_Metrics!C16/Shopee_Metrics!C12))-1,"") -> 0.33333333 | C16: =IFERROR(LN(Data!E16/Data!E12)/(LN(Data!E16/Data!E12)+LN(Shopee_Metrics!B16/Shopee_Metrics!B12)+LN(Shopee_Metrics!C16/Shopee_Metrics!C12)),"") -> 0.56492547 | D16: =IFERROR(LN(Shopee_Metrics!B16/Shopee_Metrics!B12)/(LN(Data!E16/Data!E12)+LN(Shopee_Metrics!B16/Shopee_Metrics!B12)+LN(Shopee_Metrics!C16/Shopee_Metrics!C12)),"") -> -0.11891419 | E16: =IFERROR(LN(Shopee_Metrics!C16/Shopee_Metrics!C12)/(LN(Data!E16/Data!E12)+LN(Shopee_Metrics!B16/Shopee_Metrics!B12)+LN(Shopee_Metrics!C16/Shopee_Metrics!C12)),"") -> 0.55398872
A17: =Data!A17 -> 2022Q4 | B17: =IFERROR(EXP(LN(Data!E17/Data!E13)+LN(Shopee_Metrics!B17/Shopee_Metrics!B13)+LN(Shopee_Metrics!C17/Shopee_Metrics!C13))-1,"") -> 0.38461538 | C17: =IFERROR(LN(Data!E17/Data!E13)/(LN(Data!E17/Data!E13)+LN(Shopee_Metrics!B17/Shopee_Metrics!B13)+LN(Shopee_Metrics!C17/Shopee_Metrics!C13)),"") -> -0.49940917 | D17: =IFERROR(LN(Shopee_Metrics!B17/Shopee_Metrics!B13)/(LN(Data!E17/Data!E13)+LN(Shopee_Metrics!B17/Shopee_Metrics!B13)+LN(Shopee_Metrics!C17/Shopee_Metrics!C13)),"") -> 0.4654538 | E17: =IFERROR(LN(Shopee_Metrics!C17/Shopee_Metrics!C13)/(LN(Data!E17/Data!E13)+LN(Shopee_Metrics!B17/Shopee_Metrics!B13)+LN(Shopee_Metrics!C17/Shopee_Metrics!C13)),"") -> 1.0339554
... A31: =Data!A31 -> 2026Q2 | B31: =IFERROR(EXP(LN(Data!E31/Data!E27)+LN(Shopee_Metrics!B31/Shopee_Metrics!B27)+LN(Shopee_Metrics!C31/Shopee_Metrics!C27))-1,"") -> 0.48901878 | C31: =IFERROR(LN(Data!E31/Data!E27)/(LN(Data!E31/Data!E27)+LN(Shopee_Metrics!B31/Shopee_Metrics!B27)+LN(Shopee_Metrics!C31/Shopee_Metrics!C27)),"") -> 0.60575618 | D31: =IFERROR(LN(Shopee_Metrics!B31/Shopee_Metrics!B27)/(LN(Data!E31/Data!E27)+LN(Shopee_Metrics!B31/Shopee_Metrics!B27)+LN(Shopee_Metrics!C31/Shopee_Metrics!C27)),"") -> 0.024564228 | E31: =IFERROR(LN(Shopee_Metrics!C31/Shopee_Metrics!C27)/(LN(Data!E31/Data!E27)+LN(Shopee_Metrics!B31/Shopee_Metrics!B27)+LN(Shopee_Metrics!C31/Shopee_Metrics!C27)),"") -> 0.36967959
A33: Method: log decomposition of YoY marketplace revenue growth, ln(R/R-4) = ln(orders ratio) + ln(AOV ratio) + ln(take-rate ratio); each share = its log term / total log growth.

Sheet Monee
A1: Period | B1: Monee revenue (US$ m) | C1: Monee adj. EBITDA (US$ m) | D1: Adj. EBITDA margin | E1: Loans (US$ bn) | F1: Loan basis | G1: Loan YoY (same basis only) | H1: NPL 90+ days % | I1: NPL as reported (bounds) | J1: Approx. NPL amount (US$ m) | K1: NPL vs loans 4Q earlier (seasoning view)
A2: =Data!A2 -> 2019Q1 | B2: =IF(Data!N2="","",Data!N2) | C2: =Data!O2 -> -11.912 | D2: =IF(OR(Data!N2=""),"",Data!O2/Data!N2) | E2: =IF(Data!P2="","",Data!P2) | F2: =IF(Data!Q2="","",Data!Q2) | H2: =IF(Data!R2="","",Data!R2/100) | I2: =IF(Data!S2="","",Data!S2) | J2: =IF(OR(Data!R2="",Data!P2=""),"",Data!R2/100*Data!P2*1000)
A3: =Data!A3 -> 2019Q2 | B3: =IF(Data!N3="","",Data!N3) | C3: =Data!O3 -> -18.144 | D3: =IF(OR(Data!N3=""),"",Data!O3/Data!N3) | E3: =IF(Data!P3="","",Data!P3) | F3: =IF(Data!Q3="","",Data!Q3) | H3: =IF(Data!R3="","",Data!R3/100) | I3: =IF(Data!S3="","",Data!S3) | J3: =IF(OR(Data!R3="",Data!P3=""),"",Data!R3/100*Data!P3*1000)
A4: =Data!A4 -> 2019Q3 | B4: =IF(Data!N4="","",Data!N4) | C4: =Data!O4 -> -33.628 | D4: =IF(OR(Data!N4=""),"",Data!O4/Data!N4) | E4: =IF(Data!P4="","",Data!P4) | F4: =IF(Data!Q4="","",Data!Q4) | H4: =IF(Data!R4="","",Data!R4/100) | I4: =IF(Data!S4="","",Data!S4) | J4: =IF(OR(Data!R4="",Data!P4=""),"",Data!R4/100*Data!P4*1000)
A5: =Data!A5 -> 2019Q4 | B5: =IF(Data!N5="","",Data!N5) | C5: =Data!O5 -> -49.761 | D5: =IF(OR(Data!N5=""),"",Data!O5/Data!N5) | E5: =IF(Data!P5="","",Data!P5) | F5: =IF(Data!Q5="","",Data!Q5) | H5: =IF(Data!R5="","",Data!R5/100) | I5: =IF(Data!S5="","",Data!S5) | J5: =IF(OR(Data!R5="",Data!P5=""),"",Data!R5/100*Data!P5*1000)
A6: =Data!A6 -> 2020Q1 | B6: =IF(Data!N6="","",Data!N6) | C6: =Data!O6 -> -101.583 | D6: =IF(OR(Data!N6=""),"",Data!O6/Data!N6) | E6: =IF(Data!P6="","",Data!P6) | F6: =IF(Data!Q6="","",Data!Q6) | G6: =IF(OR(Data!P6="",Data!P2="",Data!Q6<>Data!Q2),"",Data!P6/Data!P2-1) | H6: =IF(Data!R6="","",Data!R6/100) | I6: =IF(Data!S6="","",Data!S6) | J6: =IF(OR(Data!R6="",Data!P6=""),"",Data!R6/100*Data!P6*1000) | K6: =IF(OR(Data!R6="",Data!P2="",Data!Q6<>Data!Q2),"",Data!R6/100*Data!P6/Data!P2)
A7: =Data!A7 -> 2020Q2 | B7: =IF(Data!N7="","",Data!N7) | C7: =Data!O7 -> -110.105 | D7: =IF(OR(Data!N7=""),"",Data!O7/Data!N7) | E7: =IF(Data!P7="","",Data!P7) | F7: =IF(Data!Q7="","",Data!Q7) | G7: =IF(OR(Data!P7="",Data!P3="",Data!Q7<>Data!Q3),"",Data!P7/Data!P3-1) | H7: =IF(Data!R7="","",Data!R7/100) | I7: =IF(Data!S7="","",Data!S7) | J7: =IF(OR(Data!R7="",Data!P7=""),"",Data!R7/100*Data!P7*1000) | K7: =IF(OR(Data!R7="",Data!P3="",Data!Q7<>Data!Q3),"",Data!R7/100*Data!P7/Data!P3)
A8: =Data!A8 -> 2020Q3 | B8: =IF(Data!N8="","",Data!N8) | C8: =Data!O8 -> -149.263 | D8: =IF(OR(Data!N8=""),"",Data!O8/Data!N8) | E8: =IF(Data!P8="","",Data!P8) | F8: =IF(Data!Q8="","",Data!Q8) | G8: =IF(OR(Data!P8="",Data!P4="",Data!Q8<>Data!Q4),"",Data!P8/Data!P4-1) | H8: =IF(Data!R8="","",Data!R8/100) | I8: =IF(Data!S8="","",Data!S8) | J8: =IF(OR(Data!R8="",Data!P8=""),"",Data!R8/100*Data!P8*1000) | K8: =IF(OR(Data!R8="",Data!P4="",Data!Q8<>Data!Q4),"",Data!R8/100*Data!P8/Data!P4)
A9: =Data!A9 -> 2020Q4 | B9: =IF(Data!N9="","",Data!N9) | C9: =Data!O9 -> -171.263 | D9: =IF(OR(Data!N9=""),"",Data!O9/Data!N9) | E9: =IF(Data!P9="","",Data!P9) | F9: =IF(Data!Q9="","",Data!Q9) | G9: =IF(OR(Data!P9="",Data!P5="",Data!Q9<>Data!Q5),"",Data!P9/Data!P5-1) | H9: =IF(Data!R9="","",Data!R9/100) | I9: =IF(Data!S9="","",Data!S9) | J9: =IF(OR(Data!R9="",Data!P9=""),"",Data!R9/100*Data!P9*1000) | K9: =IF(OR(Data!R9="",Data!P5="",Data!Q9<>Data!Q5),"",Data!R9/100*Data!P9/Data!P5)
A10: =Data!A10 -> 2021Q1 | B10: =IF(Data!N10="","",Data!N10) | C10: =Data!O10 -> -153.088 | D10: =IF(OR(Data!N10=""),"",Data!O10/Data!N10) | E10: =IF(Data!P10="","",Data!P10) | F10: =IF(Data!Q10="","",Data!Q10) | G10: =IF(OR(Data!P10="",Data!P6="",Data!Q10<>Data!Q6),"",Data!P10/Data!P6-1) | H10: =IF(Data!R10="","",Data!R10/100) | I10: =IF(Data!S10="","",Data!S10) | J10: =IF(OR(Data!R10="",Data!P10=""),"",Data!R10/100*Data!P10*1000) | K10: =IF(OR(Data!R10="",Data!P6="",Data!Q10<>Data!Q6),"",Data!R10/100*Data!P10/Data!P6)
A11: =Data!A11 -> 2021Q2 | B11: =IF(Data!N11="","",Data!N11) | C11: =Data!O11 -> -154.986 | D11: =IF(OR(Data!N11=""),"",Data!O11/Data!N11) | E11: =IF(Data!P11="","",Data!P11) | F11: =IF(Data!Q11="","",Data!Q11) | G11: =IF(OR(Data!P11="",Data!P7="",Data!Q11<>Data!Q7),"",Data!P11/Data!P7-1) | H11: =IF(Data!R11="","",Data!R11/100) | I11: =IF(Data!S11="","",Data!S11) | J11: =IF(OR(Data!R11="",Data!P11=""),"",Data!R11/100*Data!P11*1000) | K11: =IF(OR(Data!R11="",Data!P7="",Data!Q11<>Data!Q7),"",Data!R11/100*Data!P11/Data!P7)
A12: =Data!A12 -> 2021Q3 | B12: =IF(Data!N12="","",Data!N12) | C12: =Data!O12 -> -159.037 | D12: =IF(OR(Data!N12=""),"",Data!O12/Data!N12) | E12: =IF(Data!P12="","",Data!P12) | F12: =IF(Data!Q12="","",Data!Q12) | G12: =IF(OR(Data!P12="",Data!P8="",Data!Q12<>Data!Q8),"",Data!P12/Data!P8-1) | H12: =IF(Data!R12="","",Data!R12/100) | I12: =IF(Data!S12="","",Data!S12) | J12: =IF(OR(Data!R12="",Data!P12=""),"",Data!R12/100*Data!P12*1000) | K12: =IF(OR(Data!R12="",Data!P8="",Data!Q12<>Data!Q8),"",Data!R12/100*Data!P12/Data!P8)
A13: =Data!A13 -> 2021Q4 | B13: =IF(Data!N13="","",Data!N13) -> 197.5 | C13: =Data!O13 -> -149.813 | D13: =IF(OR(Data!N13=""),"",Data!O13/Data!N13) -> -0.75854684 | E13: =IF(Data!P13="","",Data!P13) | F13: =IF(Data!Q13="","",Data!Q13) | G13: =IF(OR(Data!P13="",Data!P9="",Data!Q13<>Data!Q9),"",Data!P13/Data!P9-1) | H13: =IF(Data!R13="","",Data!R13/100) | I13: =IF(Data!S13="","",Data!S13) | J13: =IF(OR(Data!R13="",Data!P13=""),"",Data!R13/100*Data!P13*1000) | K13: =IF(OR(Data!R13="",Data!P9="",Data!Q13<>Data!Q9),"",Data!R13/100*Data!P13/Data!P9)
A14: =Data!A14 -> 2022Q1 | B14: =IF(Data!N14="","",Data!N14) -> 236 | C14: =Data!O14 -> -124.898 | D14: =IF(OR(Data!N14=""),"",Data!O14/Data!N14) -> -0.52922881 | E14: =IF(Data!P14="","",Data!P14) | F14: =IF(Data!Q14="","",Data!Q14) | G14: =IF(OR(Data!P14="",Data!P10="",Data!Q14<>Data!Q10),"",Data!P14/Data!P10-1) | H14: =IF(Data!R14="","",Data!R14/100) | I14: =IF(Data!S14="","",Data!S14) | J14: =IF(OR(Data!R14="",Data!P14=""),"",Data!R14/100*Data!P14*1000) | K14: =IF(OR(Data!R14="",Data!P10="",Data!Q14<>Data!Q10),"",Data!R14/100*Data!P14/Data!P10)
A15: =Data!A15 -> 2022Q2 | B15: =IF(Data!N15="","",Data!N15) -> 279 | C15: =Data!O15 -> -111.517 | D15: =IF(OR(Data!N15=""),"",Data!O15/Data!N15) -> -0.39970251 | E15: =IF(Data!P15="","",Data!P15) | F15: =IF(Data!Q15="","",Data!Q15) | G15: =IF(OR(Data!P15="",Data!P11="",Data!Q15<>Data!Q11),"",Data!P15/Data!P11-1) | H15: =IF(Data!R15="","",Data!R15/100) | I15: =IF(Data!S15="","",Data!S15) | J15: =IF(OR(Data!R15="",Data!P15=""),"",Data!R15/100*Data!P15*1000) | K15: =IF(OR(Data!R15="",Data!P11="",Data!Q15<>Data!Q11),"",Data!R15/100*Data!P15/Data!P11)
A16: =Data!A16 -> 2022Q3 | B16: =IF(Data!N16="","",Data!N16) -> 326.9 | C16: =Data!O16 -> -67.746 | D16: =IF(OR(Data!N16=""),"",Data!O16/Data!N16) -> -0.20723769 | E16: =IF(Data!P16="","",Data!P16) -> 2.2 | F16: =IF(Data!Q16="","",Data!Q16) -> net loans receivable, on-book | G16: =IF(OR(Data!P16="",Data!P12="",Data!Q16<>Data!Q12),"",Data!P16/Data!P12-1) | H16: =IF(Data!R16="","",Data!R16/100) | I16: =IF(Data!S16="","",Data!S16) -> <4% | J16: =IF(OR(Data!R16="",Data!P16=""),"",Data!R16/100*Data!P16*1000) | K16: =IF(OR(Data!R16="",Data!P12="",Data!Q16<>Data!Q12),"",Data!R16/100*Data!P16/Data!P12)
A17: =Data!A17 -> 2022Q4 | B17: =IF(Data!N17="","",Data!N17) -> 380.2 | C17: =Data!O17 -> 75.601 | D17: =IF(OR(Data!N17=""),"",Data!O17/Data!N17) -> 0.19884534 | E17: =IF(Data!P17="","",Data!P17) -> 2.1 | F17: =IF(Data!Q17="","",Data!Q17) -> net loans receivable, on-book | G17: =IF(OR(Data!P17="",Data!P13="",Data!Q17<>Data!Q13),"",Data!P17/Data!P13-1) | H17: =IF(Data!R17="","",Data!R17/100) | I17: =IF(Data!S17="","",Data!S17) -> <2% | J17: =IF(OR(Data!R17="",Data!P17=""),"",Data!R17/100*Data!P17*1000) | K17: =IF(OR(Data!R17="",Data!P13="",Data!Q17<>Data!Q13),"",Data!R17/100*Data!P17/Data!P13)
... A31: =Data!A31 -> 2026Q2 | B31: =IF(Data!N31="","",Data!N31) -> 1402.83 | C31: =Data!O31 -> 287.985 | D31: =IF(OR(Data!N31=""),"",Data!O31/Data!N31) -> 0.2052886 | E31: =IF(Data!P31="","",Data!P31) -> 11.1 | F31: =IF(Data!Q31="","",Data!Q31) -> principal outstanding, on- and off-book | G31: =IF(OR(Data!P31="",Data!P27="",Data!Q31<>Data!Q27),"",Data!P31/Data!P27-1) -> 0.60869565 | H31: =IF(Data!R31="","",Data!R31/100) -> 0.01 | I31: =IF(Data!S31="","",Data!S31) | J31: =IF(OR(Data!R31="",Data!P31=""),"",Data!R31/100*Data!P31*1000) -> 111 | K31: =IF(OR(Data!R31="",Data!P27="",Data!Q31<>Data!Q27),"",Data!R31/100*Data!P31/Data!P27) -> 0.016086957
A33: Seasoning view: when a loan book grows fast, new loans have not had time to go bad, which flatters the NPL ratio. Dividing today's NPL amount by the book four quarters earlier shows the ratio without that effect. Approximate: the NPL % is printed to one decimal.

Sheet Target_2026
A1: Nowcast: can Shopee reach US$1 billion adjusted EBITDA in FY2026?
A2: Sea's CEO said in the Q2 2026 release that he is 'optimistic' Shopee will reach US$1 billion adjusted EBITDA for the full year.
A3: Pre-results estimate (nowcast) made on 15 Oct 2026 from H1 2026 data, before Sea reports Q3 2026 (mid-November 2026) and FY2026 (around March 2027).
A4: Actuals (from Data)
A5: Q1 2026 adj. EBITDA (US$ m) | B5: =Data!M30 -> 223.174
A6: Q2 2026 adj. EBITDA (US$ m) | B6: =Data!M31 -> 255.419
A7: H1 2026 adj. EBITDA (US$ m) | B7: =B5+B6 -> 478.593
A8: Needed in H2 2026 for US$1 bn (US$ m) | B8: =1000-B7 -> 521.407
A9: Q3 2025 GMV (US$ bn) | B9: =Data!C28 -> 32.2
A10: Q4 2025 GMV (US$ bn) | B10: =Data!C29 -> 36.7
A11: H1 2026 GMV growth YoY | B11: =(Data!C30+Data!C31)/(Data!C26+Data!C27)-1 -> 0.29452055
A12: H2 2025 adj. EBITDA % GMV | B12: =(Data!M28+Data!M29)/((Data!C28+Data!C29)*1000) -> 0.0056387808
A13: H1 2026 adj. EBITDA % GMV | B13: =B7/((Data!C30+Data!C31)*1000) -> 0.0063305952
A14: Q2 2026 adj. EBITDA % GMV | B14: =Data!M31/(Data!C31*1000) -> 0.0066689034
A15: H2 2025 EBITDA as % of H1 2025 EBITDA (seasonality) | B15: =(Data!M28+Data!M29)/(Data!M26+Data!M27) -> 0.78948042
A17: Scenarios for H2 2026 (yellow = assumption)
B18: Bear | C18: Base | D18: Bull
A19: H2 GMV growth YoY | B19: =B11-0.05 -> 0.24452055 | C19: =B11 -> 0.29452055 | D19: =B11+0.03 -> 0.32452055
A20: H2 adj. EBITDA % GMV | B20: =B12 -> 0.0056387808 | C20: =B13 -> 0.0063305952 | D20: =B14 -> 0.0066689034
A21: Why these: Bear = growth 5 pts slower and H2 margin like H2 2025; Base = H1 2026 growth and margin; Bull = 3 pts faster growth at the Q2 2026 margin.
A23: H2 2026 GMV (US$ bn) | B23: =($B$9+$B$10)*(1+B19) -> 85.747466 | C23: =($B$9+$B$10)*(1+C19) -> 89.192466 | D23: =($B$9+$B$10)*(1+D19) -> 91.259466
A24: H2 2026 adj. EBITDA (US$ m) | B24: =B23*1000*B20 -> 483.51117 | C24: =C23*1000*C20 -> 564.6414 | D24: =D23*1000*D20 -> 608.60056
A25: FY2026 adj. EBITDA (US$ m) | B25: =$B$7+B24 -> 962.10417 | C25: =$B$7+C24 -> 1043.2344 | D25: =$B$7+D24 -> 1087.1936
A26: Gap to US$1 bn (US$ m) | B26: =B25-1000 -> -37.895833 | C26: =C25-1000 -> 43.234399 | D26: =D25-1000 -> 87.193561
A27: Reaches US$1 bn? | B27: =IF(B25>=1000,"Yes","No") -> No | C27: =IF(C25>=1000,"Yes","No") -> Yes | D27: =IF(D25>=1000,"Yes","No") -> Yes
A28: H2 margin needed for US$1 bn (% GMV) | B28: =$B$8/(B23*1000) -> 0.0060807278 | C28: =$B$8/(C23*1000) -> 0.0058458637 | D28: =$B$8/(D23*1000) -> 0.0057134566
A30: Simple seasonal check
A31: FY2026 if H2 repeats 2025's H2/H1 ratio (US$ m) | B31: =B7*(1+B15) -> 856.4328
A33: Check after Sea's Q3 2026 release (mid-November): put actual Q3 adj. EBITDA and GMV here and compare with the Base case.
A34: Actual Q3 2026 adj. EBITDA (US$ m)
A35: Actual Q3 2026 GMV (US$ bn)

Sheet Checks
A1: Data checks
A3: 1. Reported YoY vs computed YoY
A5: | period | metric | reported % | computed % | allowed gap | ok |
A6: |---|---|---|---|---|---|
A7: | 2020Q1 | gmv_usd_bn | 74.3 | 77.1 | 4.1 | yes |
A8: | 2020Q1 | gross_orders_bn | 111.2 | 111.2 | 0.3 | yes |
A9: | 2020Q2 | gmv_usd_bn | 109.9 | 110.5 | 4.3 | yes |
A10: | 2020Q2 | gross_orders_bn | 150.1 | 150.1 | 0.3 | yes |
A11: | 2020Q3 | gmv_usd_bn | 102.7 | 102.2 | 3.5 | yes |
A12: | 2020Q3 | gross_orders_bn | 130.7 | 130.7 | 0.3 | yes |
A13: | 2020Q4 | gmv_usd_bn | 112.5 | 112.5 | 3.0 | yes |
A14: | 2020Q4 | gross_orders_bn | 134.6 | 127.0 | 38.6 | yes |
... A99: 4. Remaining gaps
